pirt/README.md
pirt/__init__.py
pirt/__init__.pyi
pirt/_utils.py
pirt/_utils.pyi
pirt/deformvis.py
pirt/deformvis.pyi
pirt/experiment.py
pirt/experiment.pyi
pirt/fitting.py
pirt/fitting.pyi
pirt/gaussfun.py
pirt/gaussfun.pyi
pirt/new_pointset.py
pirt/new_pointset.pyi
pirt/py.typed
pirt/pyramid.py
pirt/pyramid.pyi
pirt/randomdeformations.py
pirt/randomdeformations.pyi
pirt/testing.py
pirt/apps/__init__.py
pirt/apps/__init__.pyi
pirt/apps/deform_by_hand.py
pirt/apps/deform_by_hand.pyi
pirt/apps/spline_by_hand.py
pirt/apps/spline_by_hand.pyi
pirt/deform/__init__.py
pirt/deform/__init__.pyi
pirt/deform/_deformbase.py
pirt/deform/_deformbase.pyi
pirt/deform/_deformfield.py
pirt/deform/_deformfield.pyi
pirt/deform/_deformgrid.py
pirt/deform/_deformgrid.pyi
pirt/deform/_subs.py
pirt/deform/_subs.pyi
pirt/interp/__init__.py
pirt/interp/__init__.pyi
pirt/interp/_backward.py
pirt/interp/_backward.pyi
pirt/interp/_backward_cuda.py
pirt/interp/_backward_cuda.pyi
pirt/interp/_cubic.py
pirt/interp/_cubic.pyi
pirt/interp/_forward.py
pirt/interp/_forward.pyi
pirt/interp/_func.py
pirt/interp/_func.pyi
pirt/interp/_misc.py
pirt/interp/_misc.pyi
pirt/interp/_sliceinvolume.py
pirt/interp/_sliceinvolume.pyi
pirt/reg/__init__.py
pirt/reg/__init__.pyi
pirt/reg/reg_base.py
pirt/reg/reg_base.pyi
pirt/reg/reg_demons.py
pirt/reg/reg_demons.pyi
pirt/reg/reg_elastix.py
pirt/reg/reg_elastix.pyi
pirt/reg/reg_gravity.py
pirt/reg/reg_gravity.pyi
pirt/splinegrid/__init__.py
pirt/splinegrid/__init__.pyi
pirt/splinegrid/_splinegridclasses.py
pirt/splinegrid/_splinegridclasses.pyi
pirt/splinegrid/_splinegridfuncs.py
pirt/splinegrid/_splinegridfuncs.pyi
sl_pirt-3.0.0.dist-info/METADATA
sl_pirt-3.0.0.dist-info/WHEEL
sl_pirt-3.0.0.dist-info/licenses/LICENSE
sl_pirt-3.0.0.dist-info/RECORD
