Metadata-Version: 2.4
Name: sl-pirt
Version: 3.0.0
Summary: Modified pirt library distribution used in the Sun lab's sl-suite2p multi-day registration pipeline.
Project-URL: Homepage, https://github.com/almarklein/pirt
Project-URL: Documentation, https://pirt.readthedocs.io/
Project-URL: Repository, https://github.com/Sun-Lab-NBB/pirt
Author: Almar Klein, Kushaan Gupta, Ivan Kondratyev
Maintainer-email: Ivan Kondratyev <ik278@cornell.edu>
License: Pirt licensing terms
License-File: LICENSE
Keywords: pirt,sl-suite2p,sunlab
Classifier: Development Status :: 5 - Production/Stable
Classifier: Intended Audience :: Science/Research
Classifier: License :: OSI Approved :: BSD License
Classifier: Operating System :: OS Independent
Classifier: Programming Language :: Python :: 3.11
Classifier: Programming Language :: Python :: 3.12
Classifier: Programming Language :: Python :: 3.13
Classifier: Topic :: Scientific/Engineering :: Image Recognition
Classifier: Topic :: Scientific/Engineering :: Medical Science Apps.
Classifier: Topic :: Scientific/Engineering :: Visualization
Requires-Python: >=3.11
Requires-Dist: numba<1,>=0.57
Requires-Dist: numpy<3,>=2
Requires-Dist: scipy<2,>=1.9
Requires-Dist: visvis<2,>=1
Provides-Extra: conda
Requires-Dist: coverage[toml]<8,>=7; extra == 'conda'
Requires-Dist: grayskull<3,>=2; extra == 'conda'
Requires-Dist: hatchling<2,>=1; extra == 'conda'
Requires-Dist: junitparser<4,>=3; extra == 'conda'
Requires-Dist: mypy<2,>=1; extra == 'conda'
Requires-Dist: pytest-cov<7,>=6; extra == 'conda'
Requires-Dist: pytest-xdist<4,>=3; extra == 'conda'
Requires-Dist: pytest<9,>=8; extra == 'conda'
Requires-Dist: ruff<1,>=0; extra == 'conda'
Requires-Dist: scipy-stubs<2,>=1; extra == 'conda'
Requires-Dist: twine<7,>=6; extra == 'conda'
Provides-Extra: condarun
Requires-Dist: numba<1,>=0.57; extra == 'condarun'
Requires-Dist: numpy<3,>=2; extra == 'condarun'
Provides-Extra: dev
Requires-Dist: ataraxis-automation<5,>=4; extra == 'dev'
Requires-Dist: build<2,>=1; extra == 'dev'
Requires-Dist: coverage[toml]<8,>=7; extra == 'dev'
Requires-Dist: grayskull<3,>=2; extra == 'dev'
Requires-Dist: hatchling<2,>=1; extra == 'dev'
Requires-Dist: junitparser<4,>=3; extra == 'dev'
Requires-Dist: mypy<2,>=1; extra == 'dev'
Requires-Dist: pytest-cov<7,>=6; extra == 'dev'
Requires-Dist: pytest-xdist<4,>=3; extra == 'dev'
Requires-Dist: pytest<9,>=8; extra == 'dev'
Requires-Dist: ruff<1,>=0; extra == 'dev'
Requires-Dist: scipy-stubs<2,>=1; extra == 'dev'
Requires-Dist: tox-uv<2,>=1; extra == 'dev'
Requires-Dist: tox<5,>=4; extra == 'dev'
Requires-Dist: twine<7,>=6; extra == 'dev'
Requires-Dist: uv<1,>=0; extra == 'dev'
Provides-Extra: noconda
Requires-Dist: ataraxis-automation<5,>=4; extra == 'noconda'
Requires-Dist: build<2,>=1; extra == 'noconda'
Requires-Dist: tox-uv<2,>=1; extra == 'noconda'
Requires-Dist: tox<5,>=4; extra == 'noconda'
Requires-Dist: uv<1,>=0; extra == 'noconda'
